functional_parsing_library/__init__.py
functional_parsing_library/asserts.py
functional_parsing_library/bind_parser.py
functional_parsing_library/check_for_empty_string.py
functional_parsing_library/fmap.py
functional_parsing_library/parser.py
functional_parsing_library/py.typed
functional_parsing_library/recursive_parser.py
functional_parsing_library/run_parser.py
functional_parsing_library/token_of_type.py
functional_parsing_library/combinators/__init__.py
functional_parsing_library/combinators/lookahead_parser.py
functional_parsing_library/combinators/maybe_parser.py
functional_parsing_library/combinators/parse_and.py
functional_parsing_library/combinators/parse_or.py
functional_parsing_library/combinators/try_parser_.py
functional_parsing_library/combinators/ignore/__init__.py
functional_parsing_library/combinators/ignore/ignore_left.py
functional_parsing_library/combinators/ignore/ignore_right.py
functional_parsing_library/combinators/sequence/__init__.py
functional_parsing_library/combinators/sequence/many.py
functional_parsing_library/combinators/sequence/n_times_parser.py
functional_parsing_library/combinators/sequence/separated_by.py
functional_parsing_library/combinators/sequence/until/__init__.py
functional_parsing_library/combinators/sequence/until/many_till.py
functional_parsing_library/combinators/sequence/until/many_till_exclusive.py
functional_parsing_library/combinators/sequence/until/some_till.py
functional_parsing_library/combinators/sequence/until/some_till_exclusive.py
functional_parsing_library/examples/__init__.py
functional_parsing_library/examples/arithmetic.py
functional_parsing_library/examples/csv_file.py
functional_parsing_library/examples/json_parser.py
functional_parsing_library/examples/person.py
functional_parsing_library/examples/version.py
functional_parsing_library/integer/__init__.py
functional_parsing_library/integer/integer.py
functional_parsing_library/strings/__init__.py
functional_parsing_library/strings/modules/__init__.py
functional_parsing_library-0.0.29.dist-info/METADATA
functional_parsing_library-0.0.29.dist-info/WHEEL
functional_parsing_library-0.0.29.dist-info/top_level.txt
functional_parsing_library-0.0.29.dist-info/RECORD
