Metadata-Version: 2.2
Name: functional_parsing_library
Version: 0.0.29
Summary: A type-safe applicative parsing library
Author-email: Wessel Bindt <wesselbindt@gmail.com>
Classifier: Programming Language :: Python :: 3
Classifier: Operating System :: OS Independent
Requires-Python: >=3.11
